Metadata-Version: 1.1
Name: contentratings
Version: 1.2.1
Summary: A small Zope 3 package (which also works with Zope 2.10+ and Five) that allows you to attach ratings to content.
Home-page: http://plone.org/products/contentratings
Author: Alec Mitchell
Author-email: apm13@columbia.edu
License: ZPL
Keywords: ratings zope plone zope3
Platform: UNKNOWN
Classifier: Intended Audience :: Developers
Classifier: License :: OSI Approved :: Zope Public License
Classifier: Programming Language :: Python
Classifier: Programming Language :: Python :: 2.6
Classifier: Programming Language :: Python :: 2.7
Classifier: Framework :: Zope3
Classifier: Framework :: Zope2
Classifier: Framework :: Plone
Classifier: Framework :: Plone :: 4.0
Classifier: Framework :: Plone :: 4.1
Classifier: Framework :: Plone :: 4.2
Classifier: Framework :: Plone :: 4.3
Classifier: Topic :: Software Development :: Libraries :: Python Modules
